_wsq.cpython-39-x86_64-linux-gnu.so
wsq/__init__.py
wsq/WsqImagePlugin.py
wsq/tests/__init__.py
wsq/tests/test.wsq
wsq/tests/test_wsq.py
wsq-0.6.dist-info/top_level.txt
wsq-0.6.dist-info/AUTHORS.rst
wsq-0.6.dist-info/METADATA
wsq-0.6.dist-info/RECORD
wsq-0.6.dist-info/LICENSE
wsq-0.6.dist-info/WHEEL
