Metadata-Version: 2.1
Name: wsq
Version: 0.6
Summary: NBIS/WSQ lib Python wrapper for Pillow
Home-page: https://github.com/idemia/python-wsq
Author: attr: wsq.__author__
Author-email: olivier.heurtier@idemia.com
License: CeCILL-C
Classifier: Development Status :: 4 - Beta
Classifier: Programming Language :: Python :: 3.8
Classifier: Programming Language :: Python :: 3.9
Classifier: Programming Language :: Python :: 3.10
Classifier: Programming Language :: Python :: 3.11
Classifier: Programming Language :: Python :: 3.12
Classifier: License :: CeCILL-C Free Software License Agreement (CECILL-C)
Requires-Python: >=3.8
License-File: LICENSE
License-File: AUTHORS.rst
Requires-Dist: Pillow
